lnschema_lamin1/__init__.py
lnschema_lamin1/models.py
lnschema_lamin1/migrations/0001_initial.py
lnschema_lamin1/migrations/0001_initial_squashed_0012.py
lnschema_lamin1/migrations/0002_alter_biosample_options_alter_experiment_options_and_more.py
lnschema_lamin1/migrations/0003_alter_biosample_created_by_and_more.py
lnschema_lamin1/migrations/0004_remove_treatment_target_genes_treatmenttarget_and_more.py
lnschema_lamin1/migrations/0005_alter_treatmenttarget_created_by_and_more.py
lnschema_lamin1/migrations/0006_remove_treatment_target_treatment_targets.py
lnschema_lamin1/migrations/0007_rename_batch_name_biosample_batch_and_more.py
lnschema_lamin1/migrations/0008_platewell_delete_well.py
lnschema_lamin1/migrations/0009_alter_platewell_id.py
lnschema_lamin1/migrations/0010_rename_platewell_well.py
lnschema_lamin1/migrations/0011_migrate_to_integer_pks.py
lnschema_lamin1/migrations/0012_export_legacy_data.py
lnschema_lamin1/migrations/0013_import_legacy_data.py
lnschema_lamin1/migrations/0014_rename_species_biosample_organism.py
lnschema_lamin1/migrations/0015_rename_files_biosample_artifacts_and_more.py
lnschema_lamin1/migrations/0016_rename_datasets_biosample_collections_and_more.py
lnschema_lamin1/migrations/0017_remove_biosample_artifacts.py
lnschema_lamin1/migrations/__init__.py
lnschema_lamin1-0.26.0.dist-info/WHEEL
lnschema_lamin1-0.26.0.dist-info/METADATA
lnschema_lamin1-0.26.0.dist-info/RECORD
