Metadata-Version: 2.1
Name: lnschema_lamin1
Version: 0.26.0
Summary: Lamin's `lamin1` exemplary lab schema.
Author-email: Lamin Labs <laminlabs@gmail.com>
Requires-Dist: lamindb[bionty]
Requires-Dist: pre-commit ; extra == "dev"
Requires-Dist: nox ; extra == "dev"
Requires-Dist: pytest>=6.0 ; extra == "dev"
Requires-Dist: pytest-cov ; extra == "dev"
Requires-Dist: nbproject_test>=0.4.1 ; extra == "dev"
Project-URL: Home, https://github.com/laminlabs/lnschema-lamin1
Provides-Extra: dev
